tableau_api_client/__init__.py
tableau_api_client/py.typed
tableau_api_client/tableau_api_client.py
tableau_api_client/attributes/__init__.py
tableau_api_client/attributes/api_version_attribute.py
tableau_api_client/attributes/on_premise_only_attribute.py
tableau_api_client/clients/__init__.py
tableau_api_client/clients/tableau_authentication.py
tableau_api_client/clients/tableau_datasources.py
tableau_api_client/clients/tableau_favorites.py
tableau_api_client/clients/tableau_flows.py
tableau_api_client/clients/tableau_jobs_tasks_schedules.py
tableau_api_client/clients/tableau_permissions.py
tableau_api_client/clients/tableau_projects.py
tableau_api_client/clients/tableau_publishing.py
tableau_api_client/clients/tableau_revisions.py
tableau_api_client/clients/tableau_server.py
tableau_api_client/clients/tableau_sites.py
tableau_api_client/clients/tableau_subscriptions.py
tableau_api_client/clients/tableau_users_groups.py
tableau_api_client/clients/tableau_workbooks_views.py
tableau_api_client/enums/__init__.py
tableau_api_client/enums/datasource_file_type.py
tableau_api_client/enums/orientation.py
tableau_api_client/enums/page_orientation.py
tableau_api_client/enums/page_type.py
tableau_api_client/enums/tableau_image_width.py
tableau_api_client/enums/workbook_file_type.py
tableau_api_client/exceptions/__init__.py
tableau_api_client/exceptions/tableau_api_version_exception.py
tableau_api_client/exceptions/tableau_online_not_supported_exception.py
tableau_api_client/exceptions/tableau_request_exception.py
tableau_api_client/models/__init__.py
tableau_api_client/models/tableau_session.py
tableau_api_client/models/ts_api.py
tableau_api_client-1.0.2.dist-info/licenses/LICENSE
tableau_api_client-1.0.2.dist-info/METADATA
tableau_api_client-1.0.2.dist-info/WHEEL
tableau_api_client-1.0.2.dist-info/top_level.txt
tableau_api_client-1.0.2.dist-info/RECORD
