Metadata-Version: 2.4
Name: tableau_api_client
Version: 1.0.2
Summary: Python client for Tableau Server REST API
Author-email: Laszlo Nemes <wow.laszlo@gmail.com>
License-Expression: MIT
Project-URL: Homepage, https://github.com/NemesLaszlo/Tableau-API-Python
Project-URL: Repository, https://github.com/NemesLaszlo/Tableau-API-Python
Project-URL: Documentation, https://github.com/NemesLaszlo/Tableau-API-Python
Project-URL: Bug Reports, https://github.com/NemesLaszlo/Tableau-API-Python/issues
Keywords: tableau,api,rest,client,server
Classifier: Operating System :: OS Independent
Classifier: Programming Language :: Python :: 3
Classifier: Topic :: Software Development :: Libraries :: Python Modules
Classifier: Topic :: Office/Business
Requires-Python: >=3.7
License-File: LICENSE
Requires-Dist: requests<3.0.0,>=2.28.0
Requires-Dist: xsdata[lxml]<25.0.0,>=23.8
Requires-Dist: typing-extensions<5.0.0,>=4.0.0
Requires-Dist: urllib3<3.0.0,>=2.5.0
Provides-Extra: test
Requires-Dist: pytest<9.0.0,>=7.0.0; extra == "test"
Dynamic: license-file
